datalayer_iam/__init__.py
datalayer_iam/__main__.py
datalayer_iam/application.py
datalayer_iam/application_base.py
datalayer_iam/authn.py
datalayer_iam/authz.py
datalayer_iam/config.py
datalayer_iam/jupyter.py
datalayer_iam/main.py
datalayer_iam/messaging.py
datalayer_iam/model.py
datalayer_iam/addons/__init__.py
datalayer_iam/addons/test.py
datalayer_iam/addons/test.yaml
datalayer_iam/api/__init__.py
datalayer_iam/api/v1/__init__.py
datalayer_iam/api/v1/openapi.yml
datalayer_iam/res/iam.svg
datalayer_iam/reserved/__init__.py
datalayer_iam/reserved/handles.py
datalayer_iam/services/__init__.py
datalayer_iam/services/accounts.py
datalayer_iam/services/credits.py
datalayer_iam/services/datasources.py
datalayer_iam/services/enterprises.py
datalayer_iam/services/github.py
datalayer_iam/services/healthz.py
datalayer_iam/services/invites.py
datalayer_iam/services/linkedin.py
datalayer_iam/services/mails.py
datalayer_iam/services/messaging.py
datalayer_iam/services/organizations.py
datalayer_iam/services/secrets.py
datalayer_iam/services/teams.py
datalayer_iam/services/tokens.py
datalayer_iam/services/usage.py
datalayer_iam/services/users.py
datalayer_iam/services/x.py
datalayer_iam/tests/__init__.py
datalayer_iam/tests/conftest.py
datalayer_iam/tests/test_jupyter.py
datalayer_iam/tests/test_users.py
datalayer_iam-0.0.11.dist-info/METADATA
datalayer_iam-0.0.11.dist-info/WHEEL
datalayer_iam-0.0.11.dist-info/entry_points.txt
datalayer_iam-0.0.11.dist-info/licenses/LICENSE
datalayer_iam-0.0.11.dist-info/RECORD
