Metadata-Version: 2.1
Name: datalayer_iam
Version: 0.0.11
License: Datalayer License
License-File: LICENSE
Classifier: Intended Audience :: Developers
Classifier: Intended Audience :: Science/Research
Classifier: Intended Audience :: System Administrators
Classifier: Programming Language :: Python
Classifier: Programming Language :: Python :: 3
Classifier: Programming Language :: Python :: 3.9
Classifier: Programming Language :: Python :: 3.10
Classifier: Programming Language :: Python :: 3.11
Classifier: Programming Language :: Python :: 3.12
Requires-Python: >=3.9
Requires-Dist: connexion==3.0.6
Requires-Dist: cryptography
Requires-Dist: datalayer-addons
Requires-Dist: datalayer-common
Requires-Dist: datalayer-solr
Requires-Dist: httpx
Requires-Dist: importlib-metadata
Requires-Dist: pulsar-client==3.5.0
Requires-Dist: pyjwt==2.8.0
Requires-Dist: starlette
Requires-Dist: tldextract
Requires-Dist: werkzeug
Provides-Extra: cli
Requires-Dist: datalayer-core; extra == 'cli'
Provides-Extra: server
Requires-Dist: connexion[uvicorn]==3.0.6; extra == 'server'
Requires-Dist: uvicorn[standard]; extra == 'server'
Provides-Extra: swagger-ui
Requires-Dist: connexion[swagger-ui]==3.0.6; extra == 'swagger-ui'
Provides-Extra: test
Requires-Dist: coverage; extra == 'test'
Requires-Dist: jupyter-server~=2.0; extra == 'test'
Requires-Dist: pyjwt[crypto]; extra == 'test'
Requires-Dist: pytest; extra == 'test'
Requires-Dist: pytest-cov; extra == 'test'
Requires-Dist: pytest-jupyter[server]>=0.4; extra == 'test'
Requires-Dist: ruff; extra == 'test'
Requires-Dist: uvicorn; extra == 'test'
